img_processing/__init__.py
img_processing/processing/__init__.py
img_processing/processing/combination.py
img_processing/processing/transformation.py
img_processing/utils/__init__.py
img_processing/utils/io.py
img_processing/utils/plot.py
img_processing_sid-0.0.1.dist-info/licenses/LICENSE
img_processing_sid-0.0.1.dist-info/METADATA
img_processing_sid-0.0.1.dist-info/WHEEL
img_processing_sid-0.0.1.dist-info/top_level.txt
img_processing_sid-0.0.1.dist-info/RECORD
