Metadata-Version: 2.4
Name: img_processing_sid
Version: 0.0.1
Summary: Pacote Python para processamento de imagens: combinação, transformação, leitura, salvamento e visualização.
Home-page: https://github.com/sidneifs/imageprocessingpackage
Author: Sidnei Silva
Author-email: supersidnei@gmail.com
Requires-Python: >=3.7
License-File: LICENSE
Dynamic: author
Dynamic: author-email
Dynamic: description
Dynamic: description-content-type
Dynamic: home-page
Dynamic: license-file
Dynamic: requires-python
Dynamic: summary
